avatar_utils/async_requests/__init__.py
avatar_utils/async_requests/async_requests.py
avatar_utils/async_requests/request_data.py
avatar_utils/async_requests/requests_result.py
avatar_utils/async_requests/response_data.py
avatar_utils/async_requests/sync_requests.py
avatar_utils/core/__init__.py
avatar_utils/core/lazy_cached_attribute.py
avatar_utils/core/version.py
avatar_utils/crawler/__init__.py
avatar_utils/crawler/adapter.py
avatar_utils/crawler/models.py
avatar_utils/db/RetryingQuery.py
avatar_utils/db/__init__.py
avatar_utils/db/mixins/__init__.py
avatar_utils/db/mixins/created_at.py
avatar_utils/db/mixins/crud.py
avatar_utils/db/mixins/json_cast.py
avatar_utils/db/mixins/sso_user.py
avatar_utils/db/mixins/time_cast.py
avatar_utils/healthz/__init__.py
avatar_utils/healthz/checker_base.py
avatar_utils/healthz/postgresql_checker.py
avatar_utils/healthz/routes.py
avatar_utils/healthz/utils.py
avatar_utils/logs/__init__.py
avatar_utils/logs/models.py
avatar_utils/logs/views.py
avatar_utils/objects/__init__.py
avatar_utils/objects/article.py
avatar_utils/objects/event.py
avatar_utils/objects/feed_item.py
avatar_utils/objects/image.py
avatar_utils/objects/interest.py
avatar_utils/objects/match.py
avatar_utils/objects/message.py
avatar_utils/objects/new.py
avatar_utils/objects/person.py
avatar_utils/objects/question.py
avatar_utils/objects/tag.py
avatar_utils/objects/abstracts/__init__.py
avatar_utils/objects/abstracts/abstract_object.py
avatar_utils/objects/abstracts/serializable.py
avatar_utils/planner_adapter/__init__.py
avatar_utils/registration/__init__.py
avatar_utils/registration/avatar.py
avatar_utils/registration/swagger.py
avatar_utils/service_accessor/__init__.py
avatar_utils/sso_helper/__init__.py
avatar_utils/sso_helper/constants.py
avatar_utils/sso_helper/flask_auth_header.py
avatar_utils/sso_helper/sso_helper.py
avatar_utils/tests/AbstractApp.py
avatar_utils/tests/BaseUnitTest.py
avatar_utils/tests/Env.py
avatar_utils/tests/IntegrationTest.py
Avatar_Utils-1.8.11.dist-info/LICENSE
Avatar_Utils-1.8.11.dist-info/METADATA
Avatar_Utils-1.8.11.dist-info/WHEEL
Avatar_Utils-1.8.11.dist-info/top_level.txt
Avatar_Utils-1.8.11.dist-info/RECORD
